quantify_scheduler/__init__.py
quantify_scheduler/_static_version.py
quantify_scheduler/_version.py
quantify_scheduler/compatibility_check.py
quantify_scheduler/compilation.py
quantify_scheduler/enums.py
quantify_scheduler/gettables.py
quantify_scheduler/gettables_profiled.py
quantify_scheduler/json_utils.py
quantify_scheduler/math.py
quantify_scheduler/pulse_compensation.py
quantify_scheduler/resources.py
quantify_scheduler/waveforms.py
quantify_scheduler/yaml_utils.py
quantify_scheduler/backends/__init__.py
quantify_scheduler/backends/circuit_to_device.py
quantify_scheduler/backends/corrections.py
quantify_scheduler/backends/graph_compilation.py
quantify_scheduler/backends/qblox_backend.py
quantify_scheduler/backends/zhinst_backend.py
quantify_scheduler/backends/mock/__init__.py
quantify_scheduler/backends/mock/mock_rom.py
quantify_scheduler/backends/qblox/__init__.py
quantify_scheduler/backends/qblox/analog.py
quantify_scheduler/backends/qblox/compiler_abc.py
quantify_scheduler/backends/qblox/compiler_container.py
quantify_scheduler/backends/qblox/conditional.py
quantify_scheduler/backends/qblox/constants.py
quantify_scheduler/backends/qblox/crosstalk_compensation.py
quantify_scheduler/backends/qblox/driver_version_check.py
quantify_scheduler/backends/qblox/enums.py
quantify_scheduler/backends/qblox/exceptions.py
quantify_scheduler/backends/qblox/hardware_config_nv_center_old_style.py
quantify_scheduler/backends/qblox/hardware_config_transmon_old_style.py
quantify_scheduler/backends/qblox/helpers.py
quantify_scheduler/backends/qblox/instrument_compilers.py
quantify_scheduler/backends/qblox/q1asm_instructions.py
quantify_scheduler/backends/qblox/qasm_program.py
quantify_scheduler/backends/qblox/qblox_acq_index_manager.py
quantify_scheduler/backends/qblox/register_manager.py
quantify_scheduler/backends/qblox/schedule.py
quantify_scheduler/backends/qblox/stack_pulses.py
quantify_scheduler/backends/qblox/timetag.py
quantify_scheduler/backends/qblox/visualization.py
quantify_scheduler-0.26.0.dist-info/licenses/AUTHORS.md
quantify_scheduler-0.26.0.dist-info/licenses/LICENSE
quantify_scheduler-0.26.0.dist-info/METADATA
quantify_scheduler-0.26.0.dist-info/WHEEL
quantify_scheduler-0.26.0.dist-info/top_level.txt
quantify_scheduler-0.26.0.dist-info/RECORD
