Metadata-Version: 2.4
Name: quantify-scheduler
Version: 0.26.0
Summary: Quantify-scheduler is a Python package for writing quantum programs featuring a hybrid gate-pulse control model with explicit timing control.
Maintainer-email: Robert Sokolewicz <rsokolewicz@qblox.com>, Amirtha Varshiny Arumugam <amirthavarshiny@orangeqs.com>, Viacheslav Ostroukh <viacheslav@orangeqs.com>, Gábor Oszkár Dénes <gdenes@qblox.com>
License: BSD-3-Clause
Project-URL: Documentation, https://quantify-os.org/docs/quantify-scheduler/
Project-URL: Source, https://gitlab.com/quantify-os/quantify-scheduler
Project-URL: Issue tracker, https://gitlab.com/quantify-os/quantify-scheduler/-/issues
Project-URL: Changelog, https://gitlab.com/quantify-os/quantify-scheduler/-/blob/main/CHANGELOG.md
Project-URL: Slack, https://join.slack.com/t/quantify-hq/shared_invite/zt-1nd78r4e9-rbWdna53cW4DO_YbtMhVuA
Project-URL: Authors, https://gitlab.com/quantify-os/quantify-scheduler/-/blob/main/AUTHORS.md
Keywords: quantum,quantify
Classifier: Development Status :: 4 - Beta
Classifier: Intended Audience :: Developers
Classifier: Intended Audience :: Science/Research
Classifier: License :: OSI Approved :: BSD License
Classifier: Natural Language :: English
Classifier: Programming Language :: Python :: 3
Classifier: Programming Language :: Python :: 3.9
Classifier: Programming Language :: Python :: 3.10
Classifier: Programming Language :: Python :: 3.11
Classifier: Programming Language :: Python :: 3.12
Classifier: Programming Language :: Python :: 3.13
Classifier: Topic :: Scientific/Engineering
Requires-Python: >=3.9
License-File: LICENSE
License-File: AUTHORS.md
Requires-Dist: columnar
Requires-Dist: dataclasses-json
Requires-Dist: eval-type-backport; python_version < "3.10"
Requires-Dist: fastjsonschema
Requires-Dist: jinja2>=3.1.2
Requires-Dist: matplotlib
Requires-Dist: networkx
Requires-Dist: numpy<2.0; python_version < "3.10"
Requires-Dist: numpy; python_version >= "3.10"
Requires-Dist: pandas[output_formatting]
Requires-Dist: pathvalidate
Requires-Dist: plotly
Requires-Dist: pydantic<2.12,>2.0
Requires-Dist: qblox-instruments<2,>=0.17.0
Requires-Dist: quantify-core>=0.8.3
Requires-Dist: qcodes>=0.32.0
Requires-Dist: scipy
Requires-Dist: xxhash
Requires-Dist: ruamel.yaml>=0.18.0
Requires-Dist: rich[jupyter]
Requires-Dist: pyqt5-qt5<=5.15.2; platform_system == "Windows"
Provides-Extra: test
Requires-Dist: pytest~=8.3; extra == "test"
Requires-Dist: pytest-mock~=3.14; extra == "test"
Requires-Dist: diff-cover~=9.2; extra == "test"
Requires-Dist: pytest-mpl~=0.17; extra == "test"
Provides-Extra: docs
Requires-Dist: jupyter-sphinx~=0.5.3; extra == "docs"
Requires-Dist: jupytext~=1.16; extra == "docs"
Requires-Dist: sphinx~=7.4; extra == "docs"
Requires-Dist: pydata-sphinx-theme~=0.16.1; extra == "docs"
Requires-Dist: myst-nb~=1.2; extra == "docs"
Requires-Dist: hvplot~=0.11.2; extra == "docs"
Requires-Dist: plotly~=6.0.1; extra == "docs"
Requires-Dist: scanpydoc~=0.14.0; extra == "docs"
Requires-Dist: sphinx-autoapi~=3.6; extra == "docs"
Requires-Dist: sphinx-autodoc-typehints<3.1; extra == "docs"
Requires-Dist: sphinx-design~=0.6.1; extra == "docs"
Requires-Dist: sphinx-jsonschema~=1.19; extra == "docs"
Requires-Dist: sphinx-togglebutton~=0.3.2; extra == "docs"
Requires-Dist: sphinx-copybutton~=0.5.2; extra == "docs"
Requires-Dist: sphinxcontrib-bibtex~=2.6; extra == "docs"
Requires-Dist: sphinxcontrib-mermaid~=1.0; extra == "docs"
Requires-Dist: quantify_scheduler[zhinst]; extra == "docs"
Provides-Extra: dev
Requires-Dist: pre-commit~=4.1; extra == "dev"
Requires-Dist: pre-commit-hooks~=5.0; extra == "dev"
Requires-Dist: pyright==1.1.396; extra == "dev"
Requires-Dist: pytest-cov~=6.0; extra == "dev"
Requires-Dist: pytest-xdist~=3.6; extra == "dev"
Requires-Dist: ruff~=0.11.0; extra == "dev"
Requires-Dist: typos~=1.30; extra == "dev"
Requires-Dist: commitizen~=4.4; extra == "dev"
Requires-Dist: sphinx-autobuild~=2024.10; extra == "dev"
Requires-Dist: quantify-scheduler[docs,test]; extra == "dev"
Provides-Extra: zhinst
Requires-Dist: zhinst==21.8.20515; python_version < "3.10" and extra == "zhinst"
Requires-Dist: zhinst-qcodes==0.1.4; python_version < "3.10" and extra == "zhinst"
Requires-Dist: zhinst-toolkit==0.1.5; python_version < "3.10" and extra == "zhinst"
Dynamic: license-file
